ner_agent/VERSION
ner_agent/__init__.py
ner_agent-0.4.1.dist-info/LICENSE
ner_agent-0.4.1.dist-info/METADATA
ner_agent-0.4.1.dist-info/WHEEL
ner_agent-0.4.1.dist-info/RECORD
