Metadata-Version: 2.3
Name: ner-agent
Version: 0.4.1
Summary: A simple NER agent
License: MIT
Author: Allen Chou
Author-email: f1470891079@gmail.com
Requires-Python: >=3.11,<4
Classifier: License :: OSI Approved :: MIT License
Classifier: Programming Language :: Python :: 3
Classifier: Programming Language :: Python :: 3.11
Classifier: Programming Language :: Python :: 3.12
Classifier: Programming Language :: Python :: 3.13
Requires-Dist: openai
Requires-Dist: openai-agents
Requires-Dist: pydantic (>=2)
Requires-Dist: str-or-none
Project-URL: Homepage, https://github.com/allen2c/ner-agent
Project-URL: PyPI, https://pypi.org/project/ner-agent/
Project-URL: Repository, https://github.com/allen2c/ner-agent
